gerridae/__init__.py
gerridae/exceptions.py
gerridae/field.py
gerridae/item.py
gerridae/log.py
gerridae/middleware.py
gerridae/request.py
gerridae/response.py
gerridae/spider.py
gerridae/utils.py
tests/__init__.py
tests/test_regex_field.py
tests/test_spider.py
gerridae-0.3.5.dist-info/METADATA
gerridae-0.3.5.dist-info/WHEEL
gerridae-0.3.5.dist-info/top_level.txt
gerridae-0.3.5.dist-info/RECORD
