Metadata-Version: 2.1
Name: gerridae
Version: 0.3.5
Summary: a crawl framework just for fun
Home-page: https://github.com/BUGLAN/gerridae
Author: buglan
Author-email: dev.buglan@gmail.com
License: UNKNOWN
Platform: UNKNOWN
Requires-Python: >=3.6
Requires-Dist: cssselect
Requires-Dist: lxml
Requires-Dist: aiohttp
